pyfastblur/__init__.py
pyfastblur/blur.py
pyfastblur/libpyfastblur/__init__.py
pyfastblur/libpyfastblur/libpng16.dll
pyfastblur/libpyfastblur/pyfastblur_cpp.pyd
pyfastblur/libpyfastblur/zlib.dll
pyfastblur/src/blur.cpp
pyfastblur/src/blur.h
pyfastblur/src/include/png.h
pyfastblur/src/include/pngconf.h
pyfastblur/src/include/pnglibconf.h
pyfastblur/src/include/zlib.h
pyfastblur/src/unix/libpng16.so
pyfastblur/src/unix/libz.so
pyfastblur/src/unix/zlib.so
pyfastblur/src/win/libpng16.dll
pyfastblur/src/win/libpng16.lib
pyfastblur/src/win/zlib.dll
pyfastblur/src/win/zlib.lib
pyfastblur-1.3.dist-info/METADATA
pyfastblur-1.3.dist-info/WHEEL
pyfastblur-1.3.dist-info/top_level.txt
pyfastblur-1.3.dist-info/RECORD
