Metadata-Version: 2.1
Name: pyfastblur
Version: 1.3
Summary: Small Python library with a single purpose to apply fast blur to PNG images (libpng backend)
Home-page: https://github.com/sertraline/pyfastblur
Author: Toshiro Iwa
Author-email: iwa@acid.im
License: UNKNOWN
Platform: UNKNOWN
